tinyargs/__init__.py
tinyargs/core.py
tinyargs-0.1.1.dist-info/licenses/LICENSE
tinyargs-0.1.1.dist-info/METADATA
tinyargs-0.1.1.dist-info/WHEEL
tinyargs-0.1.1.dist-info/top_level.txt
tinyargs-0.1.1.dist-info/RECORD
