Metadata-Version: 2.4
Name: tinyargs
Version: 0.1.1
Summary: Ultra-light command-line argument grabber for quick scripts
Author-email: Ruslan Mandell <ruslanmandell@outlook.com>
License: MIT
Project-URL: Homepage, https://github.com/RuslanAMandell/tinyargs
Project-URL: Issues, https://github.com/RuslanAMandell/tinyargs/issues
Keywords: cli,arguments,parser,minimal
Classifier: Programming Language :: Python :: 3
Classifier: License :: OSI Approved :: MIT License
Classifier: Environment :: Console
Classifier: Topic :: Software Development :: Libraries :: Python Modules
Requires-Python: >=3.9
License-File: LICENSE
Dynamic: license-file
